MANIFEST.in
README.md
setup.py
Moustache.beta.egg-info/PKG-INFO
Moustache.beta.egg-info/SOURCES.txt
Moustache.beta.egg-info/dependency_links.txt
Moustache.beta.egg-info/entry_points.txt
Moustache.beta.egg-info/requires.txt
Moustache.beta.egg-info/top_level.txt
moustache/APIDefinition.py
moustache/FileRetriever.py
moustache/FusionHelper.py
moustache/InvalidUsage.py
moustache/MoustacheCore.py
moustache/MoustacheRender.py
moustache/OdtXmlBuilder.py
moustache/__init__.py
moustache/wssecretary.py
moustache/minimal_odt/content.xml
moustache/minimal_odt/styles.xml
moustache/minimal_odt/META-INF/manifest.xml
moustache/templates/test_form.html